auth.py
constants.py
aiobitmex/__init__.py
aiobitmex/auth.py
aiobitmex/constants.py
aiobitmex/http/__init__.py
aiobitmex/ws/__init__.py
http/__init__.py
ws/__init__.py
aiobitmex-0.1.2.dist-info/LICENSE
aiobitmex-0.1.2.dist-info/METADATA
aiobitmex-0.1.2.dist-info/WHEEL
aiobitmex-0.1.2.dist-info/top_level.txt
aiobitmex-0.1.2.dist-info/RECORD
